mutt_html_reply/__init__.py
mutt_html_reply/mutt_html_reply.py
mutt_html_reply-0.5.0.dist-info/LICENSE
mutt_html_reply-0.5.0.dist-info/METADATA
mutt_html_reply-0.5.0.dist-info/WHEEL
mutt_html_reply-0.5.0.dist-info/entry_points.txt
mutt_html_reply-0.5.0.dist-info/top_level.txt
mutt_html_reply-0.5.0.dist-info/RECORD
