Metadata-Version: 2.1
Name: mutt-html-reply
Version: 0.5.0
Summary: Create an Outlook-style HTML reply
Author-email: Erik Rogers <erik@rogers-family.net>
Maintainer-email: Erik Rogers <erik@rogers-family.net>
License: Copyright © 2024 Erik Rogers
Project-URL: Repository, https://github.com/erogers88/mutt-html-reply
Keywords: mutt,html,email,reply
License-File: LICENSE
Requires-Dist: bs4
Requires-Dist: css-inline
